[
    {
        "date": "2020-09-20",
        "username": "abcd12",
        "comment": "Bendicion, venga a saciar este sediento corazon"
    },
    {
        "date": "2020-09-20",
        "username": "abcd12",
        "comment": "tocando"
    },
    {
        "date": "2020-09-20",
        "username": "abcd12",
        "comment": "dependemos de ti"
    },
    {
        "date": "2020-09-20",
        "username": "abcd12",
        "comment": "holy spirit"
    },
    {
        "date": "2020-09-20",
        "username": "abcd12",
        "comment": "yt"
    }
]